Workbook

Sheet 集計
B1: 営業G | H1: 進行管理G | I1: 業務推進室 | M1: 企画制作G | V1: 製造部 | AA1: アグリ事業部
B2: TGL | C2: KJ | D2: MY | E2: YGLH | F2: KN | G2: S | H2: N | I2: CJ | J2: HS | K2: SN | L2: KY | M2: OGLH | N2: OH | O2: IM | P2: MS | Q2: SM | R2: FK | S2: TA | T2: SS | U2: FH | V2: IMGR | W2: KGLH | X2: YGLH | Y2: SGLH | Z2: AN | AA2: KGL
A3: 2025夏 | B3: =営業!D36 -> 58 | C3: =営業!F36 -> 51 | D3: =営業!H36 -> 57 | E3: =営業!E36 -> 57 | F3: =営業!G36 -> 57 | G3: =営業!I36 -> 55 | H3: =進行管理!D29 -> 59 | I3: =事業推進!D29 -> 0 | J3: =事業推進!E29 -> 63 | K3: =事業推進!F29 -> 63 | L3: =事業推進!G29 -> 58 | M3: ='制作（デ）'!D38 -> 57 | N3: ='制作（デ）'!E38 -> 57 | O3: ='制作（デ）'!F38 -> 49 | P3: ='制作（デ）'!G38 -> 58 | Q3: ='制作（デ）'!H38 -> 60 | R3: ='制作（デ）'!I38 -> 55 | S3: ='制作（デ）'!J38 -> 58 | T3: ='制作（三）'!D30 -> 58 | U3: ='制作（外）'!D30 -> 49 | V3: ='製造部 (MGR)'!D36 -> 60 | W3: =製造部!E39 -> 52 | X3: =製造部!D39 -> 51 | Y3: =製造部!F39 -> 51 | Z3: =製造部!G39 -> 59
A4: 2025春 | B4: 56 | C4: 52 | D4: 58 | E4: 56 | F4: 55 | G4: 22 | H4: 63 | I4: 65 | J4: 66 | K4: 62 | L4: 57 | M4: 59 | N4: 58 | O4: 51 | P4: 63 | Q4: 63 | R4: 62 | S4: 64 | T4: 60 | U4: 49 | W4: 55 | X4: 56 | Y4: 56 | Z4: 58
B10: 2024夏 | C10: SMGR | D10: MGR | E10: GL | F10: GLH | K10: メンバ
A11: 75点以上 | B11: S
A12: 70点以上 | B12: A+
A13: 65点以上 | B13: A
A14: 57点以上 | B14: B+ | D14: I | E14: T | F14: O | G14: Y | J14: MY | K14: N | L14: HS | M14: SN | N14: KY | O14: SS | P14: OH | Q14: SM | R14: MS | S14: TA | T14: AN | U14: KN
A15: 50点以上 | B15: B | G15: K | H15: Y | I15: S | K15: KJ | M15: FK | N15: S
A16: 50点未満 | B16: C+ | L16: IM | M16: FH
A17: 45点未満 | B17: C
A20: 管理職評価（配分：評価３ 毎月の取組み１） | N20: 毎月の取組結果（点数換算）
A21: I MGR | B21: T GL | C21: Y GLH | D21: K GL | E21: O GLH | F21: K GLH | G21: S GLH | H21: Y GLH | M21: 部門 | N21: 3月 | O21: 4月 | P21: ５月 | Q21: ６月 | R21: 7月 | S21: 8月 | T21: 3月 | U21: 4月 | V21: ５月 | W21: ６月 | X21: 7月 | Y21: 8月 | Z21: 合計 | AA21: 換算
A22: =(A23*3+A24)/4 -> 51.5 | B22: =(B23*3+B24)/4 -> 47 | C22: =(C23*3+C24)/4 -> 40 | D22: =(D23*3+D24)/4 -> 48.5 | E22: =(E23*3+E24)/4 -> 44.25 | F22: =(F23*3+F24)/4 -> 38.5 | G22: =(G23*3+G24)/4 -> 38.5 | H22: =(H23*3+H24)/4 -> 42.5 | I22: 100点 換算 | M22: 営業 | N22: C+ | O22: C+ | P22: C | Q22: C | R22: C | T22: 2.5 | U22: 2.5 | V22: 2 | W22: 2 | X22: 2 | Z22: =SUM(T22:Y22) -> 11 | AA22: =Z22/25*100 -> 44
A23: 53.333333 | B23: 48 | C23: 38.666667 | D23: 48 | E23: 44 | F23: 36 | G23: 36 | H23: 41.333333 | I23: 管理職評価 | M23: 進行管理 | N23: D | O23: C+ | P23: C+ | Q23: C | R23: C+ | T23: 0 | U23: 2.5 | V23: 2.5 | W23: 2 | X23: 2.5 | Z23: =SUM(T23:Y23) -> 9.5 | AA23: =Z23/25*100 -> 38
A24: 46 | B24: 44 | C24: 44 | D24: 50 | E24: 45 | F24: 46 | G24: 46 | H24: 46 | I24: 毎月の取組 | M24: 事業推進 | N24: D | O24: D | P24: D | Q24: C+ | R24: C | T24: 0 | U24: 0 | V24: 0 | W24: 2.5 | X24: 2 | Z24: =SUM(T24:Y24) -> 4.5 | AA24: =Z24/25*100 -> 18
M25: 企画制作 | N25: C | O25: B- | P25: C | Q25: C | R25: C+ | T25: 2 | U25: 2.75 | V25: 2 | W25: 2 | X25: 2.5 | Z25: =SUM(T25:Y25) -> 11.25 | AA25: =Z25/25*100 -> 45
M26: 製造部 | N26: C | O26: C+ | P26: C+ | Q26: C | R26: C+ | T26: 2 | U26: 2.5 | V26: 2.5 | W26: 2 | X26: 2.5 | Z26: =SUM(T26:Y26) -> 11.5 | AA26: =Z26/25*100 -> 46
M27: アグリ | Z27: =2.5*5 -> 12.5 | AA27: =Z27/25*100 -> 50
M29: 評価 | N29: A | O29: B+ | P29: B | Q29: B- | R29: C+ | S29: C | T29: C- | U29: D
M30: 配点 | N30: 5 | O30: 4 | P30: 3 | Q30: 2.75 | R30: 2.5 | S30: 2 | T30: 1 | U30: 0
A31: ■管理職査定 集計結果配点表
A32: 2025年夏 | I32: 2025年春
A33: 獲得 点数 | B33: 管理職 レベル | C33: 等級 | D33: 評価 配点 | I33: 獲得 点数 | J33: 管理職 レベル | K33: 等級 | L33: 評価 配点
A34: 80点以上 | B34: SMGR | C34: SS | D34: 6 | I34: 80点以上 | J34: SMGR | K34: SS | L34: 6
A35: 75点以上 | B35: Mgr | C35: S | D35: 5.5 | I35: 75点以上 | J35: Mgr | K35: S | L35: 5.5
A36: 70点以上 | C36: Ａ＋＋ | D36: 5 | I36: 70点以上 | K36: Ａ＋＋ | L36: 5
A37: 65点以上 | C37: A＋ | D37: 4.5 | I37: 65点以上 | K37: A＋ | L37: 4.5 | M37: I MGR
A38: 60点以上 | B38: GL | C38: A | D38: 4 | I38: 60点以上 | J38: GL | K38: A | L38: 4
A39: 55点以上 | C39: Ｂ＋＋ | D39: 3.5 | I39: 55点以上 | K39: Ｂ＋＋ | L39: 3.5
A40: 50点以上 | C40: Ｂ＋ | D40: 3 | E40: I MGR | I40: 50点以上 | K40: Ｂ＋ | L40: 3 | O40: K GL
A41: 45点以上 | B41: GL補 サブ リーダー | C41: Ｂ | D41: 2.75 | E41: T GL | F41: K GL | I41: 45点以上 | J41: GL補 サブ リーダー | K41: Ｂ | L41: 2.75
A42: 40点以上 | C42: C＋＋ | D42: 2.5 | E42: Y GLH | F42: O GLH | G42: Y GLH | I42: 40点以上 | K42: C＋＋ | L42: 2.5 | M42: T GL | N42: O GLH | O42: Y GLH
A43: 35点以上 | C43: C＋ | D43: 2.25 | F43: S GLH | G43: K | I43: 35点以上 | K43: C＋ | L43: 2.25 | M43: Y GLH | N43: K GL | O43: S GLH
A44: 30点以上 | C44: C | D44: 2 | G44: BLH | I44: 30点以上 | K44: C | L44: 2
A45: 25点以上 | B45: GL補 候補 | D45: 1.75 | I45: 25点以上 | J45: GL補 候補 | L45: 1.75
A46: 20点以上 | D46: 1.5 | I46: 20点以上 | L46: 1.5

Sheet 営業
A1: 評価シート
A2: 評価項目 | C2: 配点
B3: 規律性 | C3: 5 | D3: 4 | E3: 2 | F3: 2 | G3: 2 | H3: 3 | I3: 4
B4: 責任感 | C4: 5 | D4: 4 | E4: 3 | F4: 3 | G4: 4 | H4: 4 | I4: 3
A5: 勤務状況 | B5: 積極性 | C5: 5 | D5: 3 | E5: 3 | F5: 3 | G5: 3 | H5: 2 | I5: 3
B6: 協調性 | C6: 5 | D6: 4 | E6: 2 | F6: 3 | G6: 3 | H6: 3 | I6: 3
B7: 社内ルールの遵守 | C7: 5 | D7: 2 | E7: 2 | F7: 3 | G7: 3 | H7: 3 | I7: 3
B8: 社会行動 | C8: 5 | D8: 4 | E8: 3 | F8: 3 | G8: 4 | H8: 3 | I8: 3
B9: 16の心得の実践 | C9: 5 | D9: 3 | E9: 3 | F9: 3 | G9: 3 | H9: 3 | I9: 3
A10: 小計 | C10: =SUM(C3:C9) -> 35 | D10: =SUM(D3:D9) -> 24 | E10: =SUM(E3:E9) -> 18 | F10: =SUM(F3:F9) -> 20 | G10: =SUM(G3:G9) -> 22 | H10: =SUM(H3:H9) -> 21 | I10: =SUM(I3:I9) -> 22
A11: 業績報告 | B11: 売上状況（前年比） | C11: 10 | D11: 8 | E11: 9 | F11: 3 | G11: 7 | H11: 9 | I11: 6 | J11: 顧客からのクレーム
B12: 売上状況（目標比） | C12: 10 | D12: 8 | E12: 9 | F12: 3 | G12: 7 | H12: 9 | I12: 4 | J12: 顧客への積極性（声かけなど）
B13: 新規顧客獲得 | C13: 10 | D13: 6 | E13: 6 | F13: 6 | G13: 6 | H13: 4 | I13: 6 | J13: 安全運転
B14: 主要顧客への訪問 | C14: 10 | D14: 4 | E14: 8 | F14: 4 | G14: 4 | H14: 4 | I14: 6 | J14: 商品の取り扱い
A15: 活動状況 | B15: 見積確認・後追い | C15: 10 | D15: 5 | E15: 6 | F15: 4 | G15: 4 | H15: 6 | I15: 2 | J15: 営業姿勢
B16: 見積内容の情報収集および上司への報連相 | C16: 10 | D16: 6 | E16: 6 | F16: 6 | G16: 6 | H16: 6 | I16: 4 | J16: 上司への報告連絡相談
B17: G取り組みへの姿勢 | C17: 10 | D17: 4 | E17: 6 | F17: 4 | G17: 2 | H17: 4 | I17: 4
A18: 小計 | C18: =SUM(C11:C17) -> 70 | D18: =SUM(D11:D17) -> 41 | E18: =SUM(E11:E17) -> 50 | F18: =SUM(F11:F17) -> 30 | G18: =SUM(G11:G17) -> 36 | H18: =SUM(H11:H17) -> 42 | I18: =SUM(I11:I17) -> 32
A19: 合計 | C19: =C10+C18 -> 105 | D19: =D10+D18 -> 65 | E19: =E10+E18 -> 68 | F19: =F10+F18 -> 50 | G19: =G10+G18 -> 58 | H19: =H10+H18 -> 63 | I19: =I10+I18 -> 54
A21: 管理者評価ウエイト | D21: 0.45 | E21: 0.35 | H21: 0.35
A22: 管理割合による評価点 | D22: =D19*(1-D21) -> 35.75 | E22: =E19*(1-E21) -> 44.2 | H22: =H19*(1-H21) -> 40.95
A24: 管理者評価 | D24: =管理職_TGL!E35 -> 36 | E24: =管理職_YGLH!F35 -> 29 | H24: =管理職_MJ!F35 -> 32
A25: 換算（100％） | D25: =D24/75*100 -> 48 | E25: =E24/75*100 -> 38.666667 | H25: =H24/75*100 -> 42.666667
A26: 管理者評価ウエイト | D26: 0.45 | E26: 0.35 | H26: 0.35
A27: 管理者加点 | D27: =D25*D26 -> 21.6 | E27: =E25*E26 -> 13.533333 | H27: =H25*H26 -> 14.933333
A29: 事故発生件数 | D29: 0 | E29: 1 | F29: 0 | G29: 1 | H29: 0 | I29: 0
A30: 無事故の加算 | D30: 1 | E30: 0 | F30: 1 | G30: 0 | H30: 1 | I30: 1
A32: 事故発生件数による加減点 | D32: =D30-D29 -> 1 | E32: =E30-E29 -> -1 | F32: =F30-F29 -> 1 | G32: =G30-G29 -> -1 | H32: =H30-H29 -> 1 | I32: =I30-I29 -> 1
A33: 上記を含めた合計ポイント | D33: =D22+D27+D32 -> 58.35 | E33: =E22+E27+E32 -> 56.733333 | F33: =F19+F32 -> 51 | G33: =G19+G32 -> 57 | H33: =H22+H27+H32 -> 56.883333 | I33: =I19+I32 -> 55
A35: 最終ポイント | D35: =D33 -> 58.35 | E35: =E33 -> 56.733333 | F35: =F33 -> 51 | G35: =G33 -> 57 | H35: =H33 -> 56.883333 | I35: =I33 -> 55
A36: 確定評価 | D36: =INT(D35+0.5) -> 58 | E36: =INT(E35+0.5) -> 57 | F36: =INT(F35+0.5) -> 51 | G36: =INT(G35+0.5) -> 57 | H36: =INT(H35+0.5) -> 57 | I36: =INT(I35+0.5) -> 55

Sheet 製造部
A1: 評価シート（製造部）
A2: 評価項目 | C2: 配点
B3: 規律性 | C3: 5 | D3: 3 | E3: 3 | F3: 3 | G3: 3
B4: 責任感 | C4: 5 | D4: 4 | E4: 3 | F4: 3 | G4: 3
A5: 勤務状況 | B5: 積極性 | C5: 5 | D5: 3 | E5: 3 | F5: 4 | G5: 3
B6: 協調性 | C6: 5 | D6: 4 | E6: 3 | F6: 3 | G6: 3
B7: 社内ルールの遵守 | C7: 5 | D7: 2 | E7: 3 | F7: 3 | G7: 3
B8: 社会行動 | C8: 5 | D8: 3 | E8: 3 | F8: 3 | G8: 3
B9: 16の心得の実践 | C9: 5 | D9: 3 | E9: 3 | F9: 2 | G9: 3
A10: 小計 | C10: =SUM(C3:C9) -> 35 | D10: =SUM(D3:D9) -> 22 | E10: =SUM(E3:E9) -> 21 | F10: =SUM(F3:F9) -> 21 | G10: =SUM(G3:G9) -> 21
A11: 業績状況 | B11: 品質に対する姿勢 | C11: 10 | D11: 5 | E11: 4 | F11: 4 | G11: 6
B12: 正確度 | C12: 10 | D12: 4 | E12: 4 | F12: 5 | G12: 6
B13: 速度（一日の作業量） | C13: 10 | D13: 7 | E13: 7 | F13: 8 | G13: 6
B14: オペレート技術（対応機種） | C14: 5 | D14: 3 | E14: 3 | F14: 3 | G14: 3
B15: 準備時間の速度 | C15: 10 | D15: 4 | E15: 7 | F15: 7 | G15: 3
A16: 活動状況 | B16: オペレート技術の向上 | C16: 5 | D16: 3 | E16: 2 | F16: 3 | G16: 3
B17: 担当機器の整備 | C17: 5 | D17: 3 | E17: 3 | F17: 2 | G17: 3
B18: 資材管理 | C18: 5 | D18: 3 | E18: 3 | F18: 2 | G18: 3
B19: 報告の適格性 | C19: 5 | D19: 3 | E19: 2 | F19: 3 | G19: 3
B20: 環境整備 | C20: 5 | D20: 3 | E20: 3 | F20: 3 | G20: 3
A21: 小計 | C21: =SUM(C11:C20) -> 70 | D21: =SUM(D11:D20) -> 38 | E21: =SUM(E11:E20) -> 38 | F21: =SUM(F11:F20) -> 40 | G21: =SUM(G11:G20) -> 39
A22: 合計 | C22: =C10+C21 -> 105 | D22: =D10+D21 -> 60 | E22: =E10+E21 -> 59 | F22: =F10+F21 -> 61 | G22: =G10+G21 -> 60
A24: 管理者評価ウエイト | D24: 0.35 | E24: 0.35 | F24: 0.35
A25: 管理割合による評価点 | D25: =D22*(1-D24) -> 39 | E25: =E22*(1-E24) -> 38.35 | F25: =F22*(1-F24) -> 39.65 | G25: =G22*(1-G24) -> 60
A27: 管理者評価 | D27: =管理職_製造!J35 -> 31 | E27: =管理職_製造!H35 -> 27 | F27: =管理職_製造!F35 -> 27
A28: 換算（100％） | D28: =D27/75*100 -> 41.333333 | E28: =E27/75*100 -> 36 | F28: =F27/75*100 -> 36
A29: 管理者評価ウエイト | D29: 0.35 | E29: 0.35 | F29: 0.35
A30: 管理者加点 | D30: =D28*D29 -> 14.466667 | E30: =E28*E29 -> 12.6 | F30: =F28*F29 -> 12.6
A32: 事故発生件数 | D32: 2 | E32: 0 | F32: 1 | G32: 1
A33: 無事故の加算 | D33: 0 | E33: 1 | F33: 0 | G33: 0
A35: 事故発生件数による加減点 | D35: =D33-D32 -> -2 | E35: =E33-E32 -> 1 | F35: =F33-F32 -> -1 | G35: =G33-G32 -> -1
A36: 上記を含めた合計ポイント | D36: =D25+D30+D35 -> 51.466667 | E36: =E25+E30+E35 -> 51.95 | F36: =F25+F30+F35 -> 51.25 | G36: =G25+G30+G35 -> 59
A38: 最終ポイント | D38: =D36 -> 51.466667 | E38: =E36 -> 51.95 | F38: =F36 -> 51.25 | G38: =G36 -> 59
A39: 確定評価 | D39: =INT(D38+0.5) -> 51 | E39: =INT(E38+0.5) -> 52 | F39: =INT(F38+0.5) -> 51 | G39: =INT(G38+0.5) -> 59

Sheet 製造部 (MGR)
A1: 評価シート（製造部）
A2: 評価項目 | C2: 配点
B3: 規律性 | C3: 5 | D3: 4
B4: 責任感 | C4: 5 | D4: 4
A5: 勤務状況 | B5: 積極性 | C5: 5 | D5: 3
B6: 協調性 | C6: 5 | D6: 3
B7: 社内ルールの遵守 | C7: 5 | D7: 4
B8: 社会行動 | C8: 5 | D8: 2
B9: 16の心得の実践 | C9: 5 | D9: 3
A10: 小計 | C10: =SUM(C3:C9) -> 35 | D10: =SUM(D3:D9) -> 23
A11: 業績状況 | B11: 品質管理 | C11: 10 | D11: 7
B12: 社内生産率の向上 | C12: 10 | D12: 5
B13: 生産量 | C13: 10 | D13: 5
A14: 活動状況 | B14: メンバー管理・育成 | C14: 10 | D14: 8
B15: 資材管理 | C15: 10 | D15: 6
B16: 職場環境 | C16: 10 | D16: 7
B17: 業務改善 | C17: 10 | D17: 5
A18: 小計 | C18: =SUM(C11:C17) -> 70 | D18: =SUM(D11:D17) -> 43
A19: 合計 | C19: =C10+C18 -> 105 | D19: =D10+D18 -> 66
A21: 管理者評価ウエイト | D21: 0.55
A22: 管理割合による評価点 | D22: =D19*(1-D21) -> 29.7
A24: 管理者評価 | D24: =管理職_IMGER!E35 -> 40
A25: 換算（100％） | D25: =D24/75*100 -> 53.333333
A26: 管理者評価ウエイト | D26: 0.55
A27: 管理者加点 | D27: =D25*D26 -> 29.333333
A29: 事故発生件数 | D29: 0
A30: 無事故の加算 | D30: 1
A32: 事故発生件数による加減点 | D32: =D30-D29 -> 1
A33: 上記を含めた合計ポイント | D33: =D22+D27+D32 -> 60.033333
A35: 最終ポイント | D35: =D33 -> 60.033333
A36: 確定評価 | D36: =INT(D35+0.5) -> 60

Sheet 事業推進
A1: 事業推進
A2: 2024.09〜2025.02
B3: 評価項目案 | C3: 配点
A4: 勤務状況 | B4: 規律性 | C4: 5 | E4: 3 | F4: 3 | G4: 3
B5: 責任感 | C5: 5 | E5: 3 | F5: 3 | G5: 3
B6: 積極性 | C6: 5 | E6: 3 | F6: 4 | G6: 3
B7: 協調性 | C7: 5 | E7: 4 | F7: 4 | G7: 2
B8: 社内ルールの遵守 | C8: 5 | E8: 3 | F8: 3 | G8: 2
B9: 社会行動 | C9: 5 | E9: 3 | F9: 4 | G9: 3
B10: 16の心得の実践 | C10: 5 | E10: 3 | F10: 3 | G10: 3
B11: 小計 | C11: =SUM(C4:C10) -> 35 | D11: =SUM(D4:D10) -> 0 | E11: =SUM(E4:E10) -> 22 | F11: =SUM(F4:F10) -> 24 | G11: =SUM(G4:G10) -> 19
A12: 業績状況 | B12: 個人目標達成状況 | C12: 10 | E12: 4 | F12: 4 | G12: 5 | I12: チームワークの項目がない
B13: 業務遂行（責任感） | C13: 10 | E13: 6 | F13: 7 | G13: 5
A14: 活動状況 | B14: 領域の拡張 | C14: 10 | E14: 6 | F14: 6 | G14: 6
B15: 時間・スケジュールの管理・計画 | C15: 10 | E15: 5 | F15: 5 | G15: 5
B16: 積極性 | C16: 10 | E16: 6 | F16: 6 | G16: 6
B17: 企画提案力 | C17: 10 | E17: 6 | F17: 5 | G17: 5
B18: コミュニケーション | C18: 10 | E18: 7 | F18: 7 | G18: 6
B19: 小計 | C19: =SUM(C12:C18) -> 70 | D19: =SUM(D12:D18) -> 0 | E19: =SUM(E12:E18) -> 40 | F19: =SUM(F12:F18) -> 40 | G19: =SUM(G12:G18) -> 38
B20: 合計 | C20: =SUM(C11,C19) -> 105 | D20: =SUM(D11,D19) -> 0 | E20: =SUM(E11,E19) -> 62 | F20: =SUM(F11,F19) -> 64 | G20: =SUM(G11,G19) -> 57
A22: 事故発生件数 | D22: 0 | E22: 0 | F22: 1 | G22: 0
A23: 無事故の加算 | D23: 0 | E23: 1 | F23: 0 | G23: 1
A25: 事故発生件数による加減点 | D25: =D23-D22 -> 0 | E25: =E23-E22 -> 1 | F25: =F23-F22 -> -1 | G25: =G23-G22 -> 1
A26: 上記を含めた合計ポイント | D26: =D20+D25 -> 0 | E26: =E20+E25 -> 63 | F26: =F20+F25 -> 63 | G26: =G20+G25 -> 58
A28: 最終ポイント | D28: =D26 -> 0 | E28: =E26 -> 63 | F28: =F26 -> 63 | G28: =G26 -> 58
A29: 確定評価 | D29: =INT(D28+0.5) -> 0 | E29: =INT(E28+0.5) -> 63 | F29: =INT(F28+0.5) -> 63 | G29: =INT(G28+0.5) -> 58

Sheet 制作（デ）
A1: 企画制作 | B1: デザインチーム
A2: 2024.09〜2025.02
B3: 評価項目案 | C3: 配点
A4: 勤務状況 | B4: 規律性 | C4: 5 | D4: 3 | E4: 3 | F4: 2 | G4: 3 | H4: 3 | I4: 2 | J4: 3
B5: 責任感 | C5: 5 | D5: 3 | E5: 3 | F5: 2 | G5: 3 | H5: 3 | I5: 3 | J5: 3
B6: 積極性 | C6: 5 | D6: 4 | E6: 3 | F6: 3 | G6: 3 | H6: 3 | I6: 3 | J6: 3
B7: 協調性 | C7: 5 | D7: 3 | E7: 3 | F7: 3 | G7: 3 | H7: 3 | I7: 3 | J7: 3
B8: 社内ルールの遵守 | C8: 5 | D8: 3 | E8: 3 | F8: 2 | G8: 2 | H8: 3 | I8: 3 | J8: 2
B9: 社会行動 | C9: 5 | D9: 3 | E9: 3 | F9: 3 | G9: 3 | H9: 3 | I9: 3 | J9: 3
B10: 16の心得の実践 | C10: 5 | D10: 4 | E10: 3 | F10: 2 | G10: 2 | H10: 3 | I10: 2 | J10: 3
B11: 小計 | C11: =SUM(C4:C10) -> 35 | D11: =SUM(D4:D10) -> 23 | E11: =SUM(E4:E10) -> 21 | F11: =SUM(F4:F10) -> 17 | G11: =SUM(G4:G10) -> 19 | H11: =SUM(H4:H10) -> 21 | I11: =SUM(I4:I10) -> 19 | J11: =SUM(J4:J10) -> 20
A12: 業績状況 | B12: 個人目標達成状況 | C12: 10 | D12: 4 | E12: 5 | F12: 3 | G12: 4 | H12: 6 | I12: 4 | J12: 5
B13: 業務遂行（責任感） | C13: 5 | D13: 3 | E13: 3 | F13: 3 | G13: 3 | H13: 3 | I13: 3 | J13: 3
B14: 技術力・デザイン力 | C14: 10 | D14: 7 | E14: 6 | F14: 5 | G14: 7 | H14: 6 | I14: 5 | J14: 6
B15: 時間・スケジュールの管理・計画 | C15: 5 | D15: 3 | E15: 3 | F15: 3 | G15: 3 | H15: 3 | I15: 3 | J15: 3
A16: 活動状況 | B16: 企画案件（コンペ） | C16: 10 | D16: 5 | E16: 4 | F16: 4 | G16: 4 | H16: 5 | I16: 6 | J16: 4
B17: コミュニケーション | C17: 10 | D17: 5 | E17: 5 | F17: 5 | G17: 6 | H17: 4 | I17: 5 | J17: 5
B18: 業務領域の拡張 | C18: 10 | D18: 5 | E18: 4 | F18: 4 | G18: 5 | H18: 5 | I18: 4 | J18: 5
B19: その他行動（期待値） | C19: 10 | D19: 6 | E19: 6 | F19: 6 | G19: 6 | H19: 6 | I19: 7 | J19: 6
B20: 小計 | C20: =SUM(C12:C19) -> 70 | D20: =SUM(D12:D19) -> 38 | E20: =SUM(E12:E19) -> 36 | F20: =SUM(F12:F19) -> 33 | G20: =SUM(G12:G19) -> 38 | H20: =SUM(H12:H19) -> 38 | I20: =SUM(I12:I19) -> 37 | J20: =SUM(J12:J19) -> 37
B21: 合計 | C21: =SUM(C11,C20) -> 105 | D21: =SUM(D11,D20) -> 61 | E21: =SUM(E11,E20) -> 57 | F21: =SUM(F11,F20) -> 50 | G21: =SUM(G11,G20) -> 57 | H21: =SUM(H11,H20) -> 59 | I21: =SUM(I11,I20) -> 56 | J21: =SUM(J11,J20) -> 57
A23: 管理者評価ウエイト | D23: 0.35
A24: 管理割合による評価点 | D24: =D21*(1-D23) -> 39.65
A26: 管理者評価 | D26: 34
A27: 換算（100％） | D27: =D26/75*100 -> 45.333333
A28: 管理者評価ウエイト | D28: 0.35
A29: 管理者加点 | D29: =D27*D28 -> 15.866667
A31: 事故発生件数 | D31: 0 | E31: 0 | F31: 1 | G31: 0 | H31: 0 | I31: 1 | J31: 0
A32: 無事故の加算 | D32: 1 | E32: 0 | F32: 0 | G32: 1 | H32: 1 | I32: 0 | J32: 1
A34: 事故発生件数による加減点 | D34: =D32-D31 -> 1 | E34: =E32-E31 -> 0 | F34: =F32-F31 -> -1 | G34: =G32-G31 -> 1 | H34: =H32-H31 -> 1 | I34: =I32-I31 -> -1 | J34: =J32-J31 -> 1
A35: 上記を含めた合計ポイント | D35: =D24+D29+D34 -> 56.516667 | E35: =E21+E34 -> 57 | F35: =F21+F34 -> 49 | G35: =G21+G34 -> 58 | H35: =H21+H34 -> 60 | I35: =I21+I34 -> 55 | J35: =J21+J34 -> 58
A37: 最終ポイント | D37: =D35 -> 56.516667 | E37: =E35 -> 57 | F37: =F35 -> 49 | G37: =G35 -> 58 | H37: =H35 -> 60 | I37: =I35 -> 55 | J37: =J35 -> 58
A38: 確定評価 | D38: =INT(D37+0.5) -> 57 | E38: =INT(E37+0.5) -> 57 | F38: =INT(F37+0.5) -> 49 | G38: =INT(G37+0.5) -> 58 | H38: =INT(H37+0.5) -> 60 | I38: =INT(I37+0.5) -> 55 | J38: =INT(J37+0.5) -> 58

Sheet 制作（三）
A1: 企画制作 | B1: 第三者・小物
A2: 2024.09〜2025.02
B3: 評価項目案 | C3: 配点
A4: 勤務状況 | B4: 規律性 | C4: 5 | D4: 3
B5: 責任感 | C5: 5 | D5: 3
B6: 積極性 | C6: 5 | D6: 3
B7: 協調性 | C7: 5 | D7: 3
B8: 社内ルールの遵守 | C8: 5 | D8: 3
B9: 社会行動 | C9: 5 | D9: 3
B10: 16の心得の実践 | C10: 5 | D10: 3
B11: 小計 | C11: =SUM(C4:C10) -> 35 | D11: =SUM(D4:D10) -> 21
A12: 業績状況 | B12: 個人目標達成状況 | C12: 10 | D12: 5
B13: 業務遂行（責任感） | C13: 5 | D13: 4
B14: 第三者校正の精度 | C14: 10 | D14: 5
B15: 時間・スケジュールの管理・計画 | C15: 5 | D15: 3
A16: 活動状況 | B16: 印刷・制作の理解力 | C16: 10 | D16: 5
B17: コミュニケーション | C17: 10 | D17: 5
B18: 業務領域の拡張 | C18: 10 | D18: 5
B19: その他行動（期待値） | C19: 10 | D19: 4
B20: 小計 | C20: =SUM(C12:C19) -> 70 | D20: =SUM(D12:D19) -> 36
B21: 合計 | C21: =SUM(C11,C20) -> 105 | D21: =SUM(D11,D20) -> 57
A23: 事故発生件数 | D23: 0
A24: 無事故の加算 | D24: 1
A26: 事故発生件数による加減点 | D26: =D24-D23 -> 1
A27: 上記を含めた合計ポイント | D27: =D21+D26 -> 58
A29: 最終ポイント | D29: =D27 -> 58
A30: 確定評価 | D30: =INT(D29+0.5) -> 58

Sheet 制作（外）
A1: 企画制作 | B1: 外注手配チーム
B3: 評価項目案 | C3: 配点
A4: 勤務状況 | B4: 規律性 | C4: 5 | D4: 2
B5: 責任感 | C5: 5 | D5: 3
B6: 積極性 | C6: 5 | D6: 3
B7: 協調性 | C7: 5 | D7: 2
B8: 社内ルールの遵守 | C8: 5 | D8: 2
B9: 社会行動 | C9: 5 | D9: 2
B10: 16の心得の実践 | C10: 5 | D10: 2
B11: 小計 | C11: =SUM(C4:C10) -> 35 | D11: =SUM(D4:D10) -> 16
A12: 業績状況 | B12: 個人目標達成状況 | C12: 10 | D12: 4
B13: 業務遂行（責任感） | C13: 5 | D13: 3
B14: オペレート技術 | C14: 10 | D14: 5
B15: 時間・スケジュールの管理・計画 | C15: 5 | D15: 3
A16: 活動状況 | B16: 印刷・制作の理解力 | C16: 10 | D16: 4
B17: コミュニケーション | C17: 10 | D17: 5
B18: 業務領域の拡張 | C18: 10 | D18: 4
B19: その他行動（期待値） | C19: 10 | D19: 6
B20: 小計 | C20: =SUM(C12:C19) -> 70 | D20: =SUM(D12:D19) -> 34
B21: 合計 | C21: =SUM(C11,C20) -> 105 | D21: =SUM(D11,D20) -> 50
A23: 事故発生件数 | D23: 1
A24: 無事故の加算 | D24: 0
A26: 事故発生件数による加減点 | D26: =D24-D23 -> -1
A27: 上記を含めた合計ポイント | D27: =D21+D26 -> 49
A29: 最終ポイント | D29: =D27 -> 49
A30: 確定評価 | D30: =INT(D29+0.5) -> 49

Sheet 進行管理
A1: 進行管理
A2: 2024.03〜2024.08
B3: 評価項目案 | C3: 配点
A4: 勤務状況 | B4: 規律性 | C4: 5 | D4: 3
B5: 責任感 | C5: 5 | D5: 3
B6: 積極性 | C6: 5 | D6: 3
B7: 協調性 | C7: 5 | D7: 3
B8: 社内ルールの遵守 | C8: 5 | D8: 3
B9: 社会行動 | C9: 5 | D9: 3
B10: 16の心得の実践 | C10: 5 | D10: 3
B11: 小計 | C11: =SUM(C4:C10) -> 35 | D11: =SUM(D4:D10) -> 21
A12: 業績状況 | B12: 個人目標達成状況 | C12: 10 | D12: 6
B13: 協力会社との交渉力・調整力 | C13: 10 | D13: 5
B14: 社内他部署との交渉力・調整力 | C14: 10 | D14: 6
A15: 活動状況 | B15: 外注手配・見積依頼の正確性 | C15: 10 | D15: 5
B16: データ収集の正確性 | C16: 10 | D16: 5
B17: 積極的なサポート姿勢 | C17: 10 | D17: 5
B18: 業務改善の意識・活動 | C18: 10 | D18: 5
B19: 小計 | C19: =SUM(C12:C18) -> 70 | D19: =SUM(D12:D18) -> 37
B20: 合計 | C20: =SUM(C11,C19) -> 105 | D20: =SUM(D11,D19) -> 58
A22: 事故発生件数 | D22: 0
A23: 無事故の加算 | D23: 1
A25: 事故発生件数による加減点 | D25: =D23-D22 -> 1
A26: 上記を含めた合計ポイント | D26: =D20+D25 -> 59
A28: 最終ポイント | D28: =D26 -> 59
A29: 確定評価 | D29: =INT(D28+0.5) -> 59

Sheet 総務
A1: 総務
A2: 2024.09〜2025.02
B3: 評価項目案 | C3: 配点 | G3: 石田常務 | H3: 池本 | I3: 宮治
A4: 勤務状況 | B4: 規律性 | C4: 5 | G4: 4 | H4: 4 | I4: 4 | J4: =SUM(G4:I4)/3 -> 4
B5: 責任感 | C5: 5 | G5: 3 | H5: 3 | I5: 4 | J5: =SUM(G5:I5)/3 -> 3.3333333
B6: 積極性 | C6: 5 | G6: 3 | H6: 3 | I6: 3 | J6: =SUM(G6:I6)/3 -> 3
B7: 協調性 | C7: 5 | G7: 3 | H7: 3 | I7: 3 | J7: =SUM(G7:I7)/3 -> 3
B8: 社内ルールの遵守 | C8: 5 | G8: 4 | H8: 4 | I8: 4 | J8: =SUM(G8:I8)/3 -> 4
B9: 社会行動 | C9: 5 | G9: 3 | H9: 3 | I9: 3 | J9: =SUM(G9:I9)/3 -> 3
B10: 16の心得の実践 | C10: 5 | G10: 3 | H10: 3 | I10: 3 | J10: =SUM(G10:I10)/3 -> 3
B11: 小計 | C11: =SUM(C4:C10) -> 35 | D11: =SUM(D4:D10) -> 0 | G11: =SUM(G4:G10) -> 23 | H11: =SUM(H4:H10) -> 23 | I11: =SUM(I4:I10) -> 24 | J11: =SUM(G11:I11)/3 -> 23.333333
A12: 経理 | B12: 経理業務（電子請求、支払い集計、納品書（売上）） | C12: 10 | G12: 6 | H12: 6 | I12: 7 | J12: =SUM(G12:I12)/3 -> 6.3333333
A13: 総務 | B13: 業務改善（コスト削減、残業時間、補助金申請、各種取得関係） | C13: 10 | G13: 6 | H13: 5 | I13: 6 | J13: =SUM(G13:I13)/3 -> 5.6666667
B14: 社内対応（コミュニケーション、社内環境） | C14: 10 | G14: 6 | H14: 5 | I14: 6 | J14: =SUM(G14:I14)/3 -> 5.6666667
B15: 勤怠管理 | C15: 10 | G15: 5 | H15: 5 | I15: 7 | J15: =SUM(G15:I15)/3 -> 5.6666667
B16: 社員の健康管理（健康診断、社会保険関係） | C16: 10 | G16: 5 | H16: 5 | I16: 5 | J16: =SUM(G16:I16)/3 -> 5
B17: 社長業務サポート | C17: 10 | G17: 4 | H17: 4 | I17: 4 | J17: =SUM(G17:I17)/3 -> 4
A18: 庶務 | B18: 顧客対応（来社・電話） | C18: 10 | G18: 5 | H18: 5 | I18: 5 | J18: =SUM(G18:I18)/3 -> 5
B19: 小計 | C19: =SUM(C12:C18) -> 70 | D19: =SUM(D12:D18) -> 0 | G19: =SUM(G12:G18) -> 37 | H19: =SUM(H12:H18) -> 35 | I19: =SUM(I12:I18) -> 40 | J19: =SUM(G19:I19)/3 -> 37.333333
B20: 合計 | C20: =SUM(C11,C19) -> 105 | D20: =SUM(D11,D19) -> 0 | G20: =SUM(G11,G19) -> 60 | H20: =SUM(H11,H19) -> 58 | I20: =SUM(I11,I19) -> 64 | J20: =SUM(G20:I20)/3 -> 60.666667
A22: 事故発生件数 | D22: 0
A23: 無事故の加算 | D23: 1
A25: 事故発生件数による加減点 | D25: =D23-D22 -> 1
A26: 上記を含めた合計ポイント | D26: =D20+D25 -> 1
A28: 最終ポイント | D28: =D26 -> 1
A29: 確定評価 | D29: =INT(D28+0.5) -> 1

Sheet 管理職_TGL
B1: 管理職評価 | D1: スマイディアの管理職に必要な基礎能力と具体的実施行動 | E1: 石田記入
A2: 番号 | B2: 大項目 | C2: 中項目 | D2: 小項目（具体的行動内容） | E2: 上司評定
A3: 1 | B3: 課題認識 | C3: 情報収集 | D3: 新聞、業界紙、インターネットに加えて、社内外の人脈を通じて、会社及び自部門に関わる情報を入手している | E3: 2
A4: 2 | C4: 分析的・本質的課題認識 | D4: 取得した情報を正確・的確に分析したうえで、自部門の課題を明らかにしている。 | E4: 2
A5: 3 | B5: 企画・立案 | C5: あるべき姿・部門目標設定 | D5: 会社方針を踏まえて、自部門のあるべき姿・目標（ゴールイメージ）を明確にしている。 | E5: 2
A6: 4 | C6: 課題設定 | D6: 部門目標を踏まえ、顧客ニーズや部外環境の動向を想定し課題を設定している。 | E6: 2
A7: 5 | D7: 部門目標を達成するために重点課題を整理し、具体的な活動計画に落とし込むための方向性をメンバーの意見も傾聴し共有できている。
A8: 6 | C8: 体制立案 | D8: 重点課題解決に必要となる組織構成・人員・予算等の体制を立案し、会社に具申している。 | E8: 1
A9: 7 | C9: 実現性のある活動計画設定 | D9: 既成概念打破・創意工夫のある活動計画を設定している。 | E9: 2
A10: 8 | D10: 論理的に考えられた活動計画である。
A11: 9 | D11: 生産性の向上のための施策を織り込んでいる。
A12: 10 | D12: タイムスケジュールまで落とし込まれている。
A13: 11 | D13: 状況の変化に対応したり、業務拡大のための複数のシナリオが想定されている。
A14: 12 | D14: メンバー一人ひとりが主体的に取り組めるように具体的活動計画を理解させている。
A15: 13 | B15: 仕事の遂行 | C15: 実行 | D15: 困難な課題であっても合理的に考え、タイミングを逸することなく決断し、結果にコミットする努力を惜しまない。 | E15: 3
A16: 14 | D16: 「できない」ではなく、できる方法やどうすればできるかを考え実践している。
A17: 15 | D17: 率先垂範でメンバーから目標となる存在になっている。
A18: 16 | B18: 周囲への働きかけ | C18: 進捗管理と支援 | D18: 自部門だけでなく会社全体の業績向上という視点をもって、他部署に協力している。 | E18: 3
A19: 17 | D19: より大きな成果を出すためには、摩擦を恐れず既存の枠組みを変えていくように周囲に働きかけている。
A20: 18 | D20: 指示や支援、相談、叱咤激励などを通じて、目標達成へのメンバーへのこだわりを駆り立てている。
A21: 19 | D21: メンバーとは率先してコミュニケーションを行い、チームワークを高めている。
A22: 20 | D22: 自分の過ちは素直に認めている。
A23: 21 | C23: メンバー育成 | D23: メンバーの育成課題を明確に、業務の割り当てや将来のキャリアを考えた育成計画を具体的に示している。 | E23: 2
A24: 22 | B24: 検証 | C24: 検証 | D24: 自部門の活動計画に対する実績を検証し、必要に応じて目標や活動計画の見直しを行っている。 | E24: 2
A25: 23 | D25: 成功例や失敗例の共有ができている。
A26: 24 | C26: リスク管理 | D26: 職場の安全（衛生）を優先した安全確保を意識し、交通ルールも遵守している。 | E26: 3
A27: 25 | D27: 自部門で予測される問題点を適宜把握しており、未然に防いでいる。
A28: 26 | C28: トラブル発生時の対応 | D28: 発生したトラブルを、重要度や優先順位の観点から必要な対応策を定め、実践している。 | E28: 4
A29: 27 | B29: 基本 | C29: ビジネス感覚 | D29: 一般教養、基本的なマネジメントや財務・会計等の知識やスキルを自ら取得し、現場で活用している。 | E29: 2
A30: 28 | D30: 自社や自部門の利益や費用（コスト）対効果を見極めて判断している。
A31: 29 | C31: 顧客志向 | D31: 顧客や取引先との交渉や折衝を円滑に行い、WIN・WINの関係になるようその関係を維持・構築している。 | E31: 3
A32: 30 | D32: ステークホルダーそれぞれのニーズを把握し、対応している。
A33: 31 | C33: 上級管理職志向 | D33: パワハラやセクハラ、また育児休業などの社内対応ルールを正しく理解し、必要がある際には対応できている。 | E33: 3
A34: 32 | D34: 自己と会社の狭間において、会社やメンバーのことを真剣に考えた言動をとっている。
B35: 評定… | C35: 以下の5段階とする | D35: 合計点 | E35: =SUM(E3:E34) -> 36
B36: 5点… | C36: 期待を大きく上回っている | D36: 100点換算（75点） | E36: =100/75*E35 -> 48
B37: 4点… | C37: 期待を上回っている
B38: 3点… | C38: ほぼ期待通りである
B39: 2点… | C39: 期待にいま一歩である
B40: 1点… | C40: 期待を大きく下回っている

Sheet 管理職_YGLH
B1: 管理職評価 | D1: スマイディアの管理職に必要な基礎能力と具体的実施行動 | E1: 辻記入 | F1: 石田記入
A2: 番号 | B2: 大項目 | C2: 中項目 | D2: 小項目（具体的行動内容） | E2: 上司評定 | F2: 上司評定
A3: 1 | B3: 課題認識 | C3: 情報収集 | D3: 新聞、業界紙、インターネットに加えて、社内外の人脈を通じて、会社及び自部門に関わる情報を入手している | E3: 1 | F3: 1
A4: 2 | C4: 分析的・本質的課題認識 | D4: 取得した情報を正確・的確に分析したうえで、自部門の課題を明らかにしている。 | E4: 1 | F4: 1
A5: 3 | B5: 企画・立案 | C5: あるべき姿・部門目標設定 | D5: 会社方針を踏まえて、自部門のあるべき姿・目標（ゴールイメージ）を明確にしている。 | E5: 3 | F5: 2
A6: 4 | C6: 課題設定 | D6: 部門目標を踏まえ、顧客ニーズや部外環境の動向を想定し課題を設定している。 | E6: 2 | F6: 2
A7: 5 | D7: 部門目標を達成するために重点課題を整理し、具体的な活動計画に落とし込むための方向性をメンバーの意見も傾聴し共有できている。
A8: 6 | C8: 体制立案 | D8: 重点課題解決に必要となる組織構成・人員・予算等の体制を立案し、会社に具申している。 | E8: 1 | F8: 1
A9: 7 | C9: 実現性のある活動計画設定 | D9: 既成概念打破・創意工夫のある活動計画を設定している。 | E9: 2 | F9: 2
A10: 8 | D10: 論理的に考えられた活動計画である。
A11: 9 | D11: 生産性の向上のための施策を織り込んでいる。
A12: 10 | D12: タイムスケジュールまで落とし込まれている。
A13: 11 | D13: 状況の変化に対応したり、業務拡大のための複数のシナリオが想定されている。
A14: 12 | D14: メンバー一人ひとりが主体的に取り組めるように具体的活動計画を理解させている。
A15: 13 | B15: 仕事の遂行 | C15: 実行 | D15: 困難な課題であっても合理的に考え、タイミングを逸することなく決断し、結果にコミットする努力を惜しまない。 | E15: 2 | F15: 2
A16: 14 | D16: 「できない」ではなく、できる方法やどうすればできるかを考え実践している。
A17: 15 | D17: 率先垂範でメンバーから目標となる存在になっている。
A18: 16 | B18: 周囲への働きかけ | C18: 進捗管理と支援 | D18: 自部門だけでなく会社全体の業績向上という視点をもって、他部署に協力している。 | E18: 2 | F18: 2
A19: 17 | D19: より大きな成果を出すためには、摩擦を恐れず既存の枠組みを変えていくように周囲に働きかけている。
A20: 18 | D20: 指示や支援、相談、叱咤激励などを通じて、目標達成へのメンバーへのこだわりを駆り立てている。
A21: 19 | D21: メンバーとは率先してコミュニケーションを行い、チームワークを高めている。
A22: 20 | D22: 自分の過ちは素直に認めている。
A23: 21 | C23: メンバー育成 | D23: メンバーの育成課題を明確に、業務の割り当てや将来のキャリアを考えた育成計画を具体的に示している。 | E23: 1 | F23: 1
A24: 22 | B24: 検証 | C24: 検証 | D24: 自部門の活動計画に対する実績を検証し、必要に応じて目標や活動計画の見直しを行っている。 | E24: 2 | F24: 2
A25: 23 | D25: 成功例や失敗例の共有ができている。
A26: 24 | C26: リスク管理 | D26: 職場の安全（衛生）を優先した安全確保を意識し、交通ルールも遵守している。 | E26: 2 | F26: 2
A27: 25 | D27: 自部門で予測される問題点を適宜把握しており、未然に防いでいる。
A28: 26 | C28: トラブル発生時の対応 | D28: 発生したトラブルを、重要度や優先順位の観点から必要な対応策を定め、実践している。 | E28: 2 | F28: 3
A29: 27 | B29: 基本 | C29: ビジネス感覚 | D29: 一般教養、基本的なマネジメントや財務・会計等の知識やスキルを自ら取得し、現場で活用している。 | E29: 2 | F29: 2
A30: 28 | D30: 自社や自部門の利益や費用（コスト）対効果を見極めて判断している。
A31: 29 | C31: 顧客志向 | D31: 顧客や取引先との交渉や折衝を円滑に行い、WIN・WINの関係になるようその関係を維持・構築している。 | E31: 3 | F31: 3
A32: 30 | D32: ステークホルダーそれぞれのニーズを把握し、対応している。
A33: 31 | C33: 上級管理職志向 | D33: パワハラやセクハラ、また育児休業などの社内対応ルールを正しく理解し、必要がある際には対応できている。 | E33: 5 | F33: 3
A34: 32 | D34: 自己と会社の狭間において、会社やメンバーのことを真剣に考えた言動をとっている。
B35: 評定… | C35: 以下の5段階とする | D35: 合計点 | E35: =SUM(E3:E34) -> 31 | F35: =SUM(F3:F34) -> 29
B36: 5点… | C36: 期待を大きく上回っている | D36: 100点換算（75点） | F36: =100/75*F35 -> 38.666667
B37: 4点… | C37: 期待を上回っている
B38: 3点… | C38: ほぼ期待通りである
B39: 2点… | C39: 期待にいま一歩である
B40: 1点… | C40: 期待を大きく下回っている

Sheet 管理職_MJ
B1: 管理職評価 | D1: スマイディアの管理職に必要な基礎能力と具体的実施行動 | E1: 辻記入 | F1: 石田記入
A2: 番号 | B2: 大項目 | C2: 中項目 | D2: 小項目（具体的行動内容） | E2: 上司評定 | F2: 上司評定
A3: 1 | B3: 課題認識 | C3: 情報収集 | D3: 新聞、業界紙、インターネットに加えて、社内外の人脈を通じて、会社及び自部門に関わる情報を入手している | E3: 3 | F3: 2
A4: 2 | C4: 分析的・本質的課題認識 | D4: 取得した情報を正確・的確に分析したうえで、自部門の課題を明らかにしている。 | E4: 2 | F4: 1
A5: 3 | B5: 企画・立案 | C5: あるべき姿・部門目標設定 | D5: 会社方針を踏まえて、自部門のあるべき姿・目標（ゴールイメージ）を明確にしている。 | E5: 3 | F5: 2
A6: 4 | C6: 課題設定 | D6: 部門目標を踏まえ、顧客ニーズや部外環境の動向を想定し課題を設定している。 | E6: 2 | F6: 2
A7: 5 | D7: 部門目標を達成するために重点課題を整理し、具体的な活動計画に落とし込むための方向性をメンバーの意見も傾聴し共有できている。
A8: 6 | C8: 体制立案 | D8: 重点課題解決に必要となる組織構成・人員・予算等の体制を立案し、会社に具申している。 | E8: 2 | F8: 1
A9: 7 | C9: 実現性のある活動計画設定 | D9: 既成概念打破・創意工夫のある活動計画を設定している。 | E9: 3 | F9: 2
A10: 8 | D10: 論理的に考えられた活動計画である。
A11: 9 | D11: 生産性の向上のための施策を織り込んでいる。
A12: 10 | D12: タイムスケジュールまで落とし込まれている。
A13: 11 | D13: 状況の変化に対応したり、業務拡大のための複数のシナリオが想定されている。
A14: 12 | D14: メンバー一人ひとりが主体的に取り組めるように具体的活動計画を理解させている。
A15: 13 | B15: 仕事の遂行 | C15: 実行 | D15: 困難な課題であっても合理的に考え、タイミングを逸することなく決断し、結果にコミットする努力を惜しまない。 | E15: 3 | F15: 3
A16: 14 | D16: 「できない」ではなく、できる方法やどうすればできるかを考え実践している。
A17: 15 | D17: 率先垂範でメンバーから目標となる存在になっている。
A18: 16 | B18: 周囲への働きかけ | C18: 進捗管理と支援 | D18: 自部門だけでなく会社全体の業績向上という視点をもって、他部署に協力している。 | E18: 3 | F18: 3
A19: 17 | D19: より大きな成果を出すためには、摩擦を恐れず既存の枠組みを変えていくように周囲に働きかけている。
A20: 18 | D20: 指示や支援、相談、叱咤激励などを通じて、目標達成へのメンバーへのこだわりを駆り立てている。
A21: 19 | D21: メンバーとは率先してコミュニケーションを行い、チームワークを高めている。
A22: 20 | D22: 自分の過ちは素直に認めている。
A23: 21 | C23: メンバー育成 | D23: メンバーの育成課題を明確に、業務の割り当てや将来のキャリアを考えた育成計画を具体的に示している。 | E23: 2 | F23: 1
A24: 22 | B24: 検証 | C24: 検証 | D24: 自部門の活動計画に対する実績を検証し、必要に応じて目標や活動計画の見直しを行っている。 | E24: 2 | F24: 2
A25: 23 | D25: 成功例や失敗例の共有ができている。
A26: 24 | C26: リスク管理 | D26: 職場の安全（衛生）を優先した安全確保を意識し、交通ルールも遵守している。 | E26: 2 | F26: 2
A27: 25 | D27: 自部門で予測される問題点を適宜把握しており、未然に防いでいる。
A28: 26 | C28: トラブル発生時の対応 | D28: 発生したトラブルを、重要度や優先順位の観点から必要な対応策を定め、実践している。 | E28: 3 | F28: 3
A29: 27 | B29: 基本 | C29: ビジネス感覚 | D29: 一般教養、基本的なマネジメントや財務・会計等の知識やスキルを自ら取得し、現場で活用している。 | E29: 2 | F29: 2
A30: 28 | D30: 自社や自部門の利益や費用（コスト）対効果を見極めて判断している。
A31: 29 | C31: 顧客志向 | D31: 顧客や取引先との交渉や折衝を円滑に行い、WIN・WINの関係になるようその関係を維持・構築している。 | E31: 3 | F31: 3
A32: 30 | D32: ステークホルダーそれぞれのニーズを把握し、対応している。
A33: 31 | C33: 上級管理職志向 | D33: パワハラやセクハラ、また育児休業などの社内対応ルールを正しく理解し、必要がある際には対応できている。 | E33: 3 | F33: 3
A34: 32 | D34: 自己と会社の狭間において、会社やメンバーのことを真剣に考えた言動をとっている。
B35: 評定… | C35: 以下の5段階とする | D35: 評価合計（75点） | E35: =SUM(E3:E34) -> 38 | F35: =SUM(F3:F34) -> 32
B36: 5点… | C36: 期待を大きく上回っている | D36: 100点換算（75点） | F36: =100/75*F35 -> 42.666667
B37: 4点… | C37: 期待を上回っている
B38: 3点… | C38: ほぼ期待通りである
B39: 2点… | C39: 期待にいま一歩である
B40: 1点… | C40: 期待を大きく下回っている

Sheet 管理職_MGLH
B1: 管理職評価 | D1: スマイディアの管理職に必要な基礎能力と具体的実施行動
A2: 番号 | B2: 大項目 | C2: 中項目 | D2: 小項目（具体的行動内容） | E2: 上司評定
A3: 1 | B3: 課題認識 | C3: 情報収集 | D3: 新聞、業界紙、インターネットに加えて、社内外の人脈を通じて、会社及び自部門に関わる情報を入手している | E3: 2
A4: 2 | C4: 分析的・本質的課題認識 | D4: 取得した情報を正確・的確に分析したうえで、自部門の課題を明らかにしている。 | E4: 2
A5: 3 | B5: 企画・立案 | C5: あるべき姿・部門目標設定 | D5: 会社方針を踏まえて、自部門のあるべき姿・目標（ゴールイメージ）を明確にしている。 | E5: 2
A6: 4 | C6: 課題設定 | D6: 部門目標を踏まえ、顧客ニーズや部外環境の動向を想定し課題を設定している。 | E6: 2
A7: 5 | D7: 部門目標を達成するために重点課題を整理し、具体的な活動計画に落とし込むための方向性をメンバーの意見も傾聴し共有できている。
A8: 6 | C8: 体制立案 | D8: 重点課題解決に必要となる組織構成・人員・予算等の体制を立案し、会社に具申している。 | E8: 1
A9: 7 | C9: 実現性のある活動計画設定 | D9: 既成概念打破・創意工夫のある活動計画を設定している。 | E9: 2
A10: 8 | D10: 論理的に考えられた活動計画である。
A11: 9 | D11: 生産性の向上のための施策を織り込んでいる。
A12: 10 | D12: タイムスケジュールまで落とし込まれている。
A13: 11 | D13: 状況の変化に対応したり、業務拡大のための複数のシナリオが想定されている。
A14: 12 | D14: メンバー一人ひとりが主体的に取り組めるように具体的活動計画を理解させている。
A15: 13 | B15: 仕事の遂行 | C15: 実行 | D15: 困難な課題であっても合理的に考え、タイミングを逸することなく決断し、結果にコミットする努力を惜しまない。 | E15: 2
A16: 14 | D16: 「できない」ではなく、できる方法やどうすればできるかを考え実践している。
A17: 15 | D17: 率先垂範でメンバーから目標となる存在になっている。
A18: 16 | B18: 周囲への働きかけ | C18: 進捗管理と支援 | D18: 自部門だけでなく会社全体の業績向上という視点をもって、他部署に協力している。 | E18: 2
A19: 17 | D19: より大きな成果を出すためには、摩擦を恐れず既存の枠組みを変えていくように周囲に働きかけている。
A20: 18 | D20: 指示や支援、相談、叱咤激励などを通じて、目標達成へのメンバーへのこだわりを駆り立てている。
A21: 19 | D21: メンバーとは率先してコミュニケーションを行い、チームワークを高めている。
A22: 20 | D22: 自分の過ちは素直に認めている。
A23: 21 | C23: メンバー育成 | D23: メンバーの育成課題を明確に、業務の割り当てや将来のキャリアを考えた育成計画を具体的に示している。 | E23: 3
A24: 22 | B24: 検証 | C24: 検証 | D24: 自部門の活動計画に対する実績を検証し、必要に応じて目標や活動計画の見直しを行っている。 | E24: 2
A25: 23 | D25: 成功例や失敗例の共有ができている。
A26: 24 | C26: リスク管理 | D26: 職場の安全（衛生）を優先した安全確保を意識し、交通ルールも遵守している。 | E26: 3
A27: 25 | D27: 自部門で予測される問題点を適宜把握しており、未然に防いでいる。
A28: 26 | C28: トラブル発生時の対応 | D28: 発生したトラブルを、重要度や優先順位の観点から必要な対応策を定め、実践している。 | E28: 3
A29: 27 | B29: 基本 | C29: ビジネス感覚 | D29: 一般教養、基本的なマネジメントや財務・会計等の知識やスキルを自ら取得し、現場で活用している。 | E29: 2
A30: 28 | D30: 自社や自部門の利益や費用（コスト）対効果を見極めて判断している。
A31: 29 | C31: 顧客志向 | D31: 顧客や取引先との交渉や折衝を円滑に行い、WIN・WINの関係になるようその関係を維持・構築している。 | E31: 2
A32: 30 | D32: ステークホルダーそれぞれのニーズを把握し、対応している。
A33: 31 | C33: 上級管理職志向 | D33: パワハラやセクハラ、また育児休業などの社内対応ルールを正しく理解し、必要がある際には対応できている。 | E33: 3
A34: 32 | D34: 自己と会社の狭間において、会社やメンバーのことを真剣に考えた言動をとっている。
B35: 評定… | C35: 以下の5段階とする | D35: 合計点 | E35: =SUM(E3:E34) -> 33
B36: 5点… | C36: 期待を大きく上回っている | D36: 100点換算（75点） | E36: =100/75*E35 -> 44
B37: 4点… | C37: 期待を上回っている
B38: 3点… | C38: ほぼ期待通りである
B39: 2点… | C39: 期待にいま一歩である
B40: 1点… | C40: 期待を大きく下回っている

Sheet 管理職_製造
B1: 管理職評価 | D1: スマイディアの管理職に必要な基礎能力と具体的実施行動
A2: 番号 | B2: 大項目 | C2: 中項目 | D2: 小項目（具体的行動内容） | E2: 上司評定 | F2: 常務評価 | G2: 上司評定 | H2: 常務評価 | I2: 上司評価 | J2: 常務評価
A3: 1 | B3: 課題認識 | C3: 情報収集 | D3: 新聞、業界紙、インターネットに加えて、社内外の人脈を通じて、会社及び自部門に関わる情報を入手している | E3: 2 | F3: 1 | G3: 2 | H3: 1 | I3: 2 | J3: 1
A4: 2 | C4: 分析的・本質的課題認識 | D4: 取得した情報を正確・的確に分析したうえで、自部門の課題を明らかにしている。 | E4: 2 | F4: 1 | G4: 2 | H4: 1 | I4: 2 | J4: 1
A5: 3 | B5: 企画・立案 | C5: あるべき姿・部門目標設定 | D5: 会社方針を踏まえて、自部門のあるべき姿・目標（ゴールイメージ）を明確にしている。 | E5: 2 | F5: 2 | G5: 2 | H5: 2 | I5: 2 | J5: 2
A6: 4 | C6: 課題設定 | D6: 部門目標を踏まえ、顧客ニーズや部外環境の動向を想定し課題を設定している。 | E6: 3 | F6: 2 | G6: 3 | H6: 2 | I6: 3 | J6: 3
A7: 5 | D7: 部門目標を達成するために重点課題を整理し、具体的な活動計画に落とし込むための方向性をメンバーの意見も傾聴し共有できている。
A8: 6 | C8: 体制立案 | D8: 重点課題解決に必要となる組織構成・人員・予算等の体制を立案し、会社に具申している。 | E8: 2 | F8: 1 | G8: 2 | H8: 1 | I8: 2 | J8: 2
A9: 7 | C9: 実現性のある活動計画設定 | D9: 既成概念打破・創意工夫のある活動計画を設定している。 | E9: 3 | F9: 2 | G9: 2 | H9: 1 | I9: 2 | J9: 2
A10: 8 | D10: 論理的に考えられた活動計画である。
A11: 9 | D11: 生産性の向上のための施策を織り込んでいる。
A12: 10 | D12: タイムスケジュールまで落とし込まれている。
A13: 11 | D13: 状況の変化に対応したり、業務拡大のための複数のシナリオが想定されている。
A14: 12 | D14: メンバー一人ひとりが主体的に取り組めるように具体的活動計画を理解させている。
A15: 13 | B15: 仕事の遂行 | C15: 実行 | D15: 困難な課題であっても合理的に考え、タイミングを逸することなく決断し、結果にコミットする努力を惜しまない。 | E15: 2 | F15: 2 | G15: 2 | H15: 2 | I15: 2 | J15: 2
A16: 14 | D16: 「できない」ではなく、できる方法やどうすればできるかを考え実践している。
A17: 15 | D17: 率先垂範でメンバーから目標となる存在になっている。
A18: 16 | B18: 周囲への働きかけ | C18: 進捗管理と支援 | D18: 自部門だけでなく会社全体の業績向上という視点をもって、他部署に協力している。 | E18: 3 | F18: 2 | G18: 2 | H18: 2 | I18: 3 | J18: 3
A19: 17 | D19: より大きな成果を出すためには、摩擦を恐れず既存の枠組みを変えていくように周囲に働きかけている。
A20: 18 | D20: 指示や支援、相談、叱咤激励などを通じて、目標達成へのメンバーへのこだわりを駆り立てている。
A21: 19 | D21: メンバーとは率先してコミュニケーションを行い、チームワークを高めている。
A22: 20 | D22: 自分の過ちは素直に認めている。
A23: 21 | C23: メンバー育成 | D23: メンバーの育成課題を明確に、業務の割り当てや将来のキャリアを考えた育成計画を具体的に示している。 | E23: 2 | F23: 1 | G23: 2 | H23: 2 | I23: 2 | J23: 1
A24: 22 | B24: 検証 | C24: 検証 | D24: 自部門の活動計画に対する実績を検証し、必要に応じて目標や活動計画の見直しを行っている。 | E24: 2 | F24: 2 | G24: 2 | H24: 2 | I24: 2 | J24: 2
A25: 23 | D25: 成功例や失敗例の共有ができている。
A26: 24 | C26: リスク管理 | D26: 職場の安全（衛生）を優先した安全確保を意識し、交通ルールも遵守している。 | E26: 3 | F26: 2 | G26: 3 | H26: 2 | I26: 3 | J26: 3
A27: 25 | D27: 自部門で予測される問題点を適宜把握しており、未然に防いでいる。
A28: 26 | C28: トラブル発生時の対応 | D28: 発生したトラブルを、重要度や優先順位の観点から必要な対応策を定め、実践している。 | E28: 2 | F28: 3 | G28: 2 | H28: 3 | I28: 2 | J28: 3
A29: 27 | B29: 基本 | C29: ビジネス感覚 | D29: 一般教養、基本的なマネジメントや財務・会計等の知識やスキルを自ら取得し、現場で活用している。 | E29: 2 | F29: 2 | G29: 2 | H29: 2 | I29: 2 | J29: 2
A30: 28 | D30: 自社や自部門の利益や費用（コスト）対効果を見極めて判断している。
A31: 29 | C31: 顧客志向 | D31: 顧客や取引先との交渉や折衝を円滑に行い、WIN・WINの関係になるようその関係を維持・構築している。 | E31: 2 | F31: 1 | G31: 2 | H31: 1 | I31: 2 | J31: 1
A32: 30 | D32: ステークホルダーそれぞれのニーズを把握し、対応している。
A33: 31 | C33: 上級管理職志向 | D33: パワハラやセクハラ、また育児休業などの社内対応ルールを正しく理解し、必要がある際には対応できている。 | E33: 3 | F33: 3 | G33: 3 | H33: 3 | I33: 3 | J33: 3
A34: 32 | D34: 自己と会社の狭間において、会社やメンバーのことを真剣に考えた言動をとっている。
B35: 評定… | C35: 以下の5段階とする | D35: 合計点 | E35: =SUM(E3:E34) -> 35 | F35: =SUM(F3:F34) -> 27 | G35: =SUM(G3:G34) -> 33 | H35: =SUM(H3:H34) -> 27 | I35: =SUM(I3:I34) -> 34 | J35: =SUM(J3:J34) -> 31
B36: 5点… | C36: 期待を大きく上回っている | D36: 100点換算（75点） | F36: =100/75*F35 -> 36 | H36: =100/75*H35 -> 36 | J36: =100/75*J35 -> 41.333333
B37: 4点… | C37: 期待を上回っている
B38: 3点… | C38: ほぼ期待通りである
B39: 2点… | C39: 期待にいま一歩である
B40: 1点… | C40: 期待を大きく下回っている

Sheet 管理職_IMGER
B1: 管理職評価 | D1: スマイディアの管理職に必要な基礎能力と具体的実施行動
A2: 番号 | B2: 大項目 | C2: 中項目 | D2: 小項目（具体的行動内容） | E2: 上司評定
A3: 1 | B3: 課題認識 | C3: 情報収集 | D3: 新聞、業界紙、インターネットに加えて、社内外の人脈を通じて、会社及び自部門に関わる情報を入手している | E3: 2
A4: 2 | C4: 分析的・本質的課題認識 | D4: 取得した情報を正確・的確に分析したうえで、自部門の課題を明らかにしている。 | E4: 2
A5: 3 | B5: 企画・立案 | C5: あるべき姿・部門目標設定 | D5: 会社方針を踏まえて、自部門のあるべき姿・目標（ゴールイメージ）を明確にしている。 | E5: 3
A6: 4 | C6: 課題設定 | D6: 部門目標を踏まえ、顧客ニーズや部外環境の動向を想定し課題を設定している。 | E6: 2
A7: 5 | D7: 部門目標を達成するために重点課題を整理し、具体的な活動計画に落とし込むための方向性をメンバーの意見も傾聴し共有できている。
A8: 6 | C8: 体制立案 | D8: 重点課題解決に必要となる組織構成・人員・予算等の体制を立案し、会社に具申している。 | E8: 3
A9: 7 | C9: 実現性のある活動計画設定 | D9: 既成概念打破・創意工夫のある活動計画を設定している。 | E9: 3
A10: 8 | D10: 論理的に考えられた活動計画である。
A11: 9 | D11: 生産性の向上のための施策を織り込んでいる。
A12: 10 | D12: タイムスケジュールまで落とし込まれている。
A13: 11 | D13: 状況の変化に対応したり、業務拡大のための複数のシナリオが想定されている。
A14: 12 | D14: メンバー一人ひとりが主体的に取り組めるように具体的活動計画を理解させている。
A15: 13 | B15: 仕事の遂行 | C15: 実行 | D15: 困難な課題であっても合理的に考え、タイミングを逸することなく決断し、結果にコミットする努力を惜しまない。 | E15: 3
A16: 14 | D16: 「できない」ではなく、できる方法やどうすればできるかを考え実践している。
A17: 15 | D17: 率先垂範でメンバーから目標となる存在になっている。
A18: 16 | B18: 周囲への働きかけ | C18: 進捗管理と支援 | D18: 自部門だけでなく会社全体の業績向上という視点をもって、他部署に協力している。 | E18: 3
A19: 17 | D19: より大きな成果を出すためには、摩擦を恐れず既存の枠組みを変えていくように周囲に働きかけている。
A20: 18 | D20: 指示や支援、相談、叱咤激励などを通じて、目標達成へのメンバーへのこだわりを駆り立てている。
A21: 19 | D21: メンバーとは率先してコミュニケーションを行い、チームワークを高めている。
A22: 20 | D22: 自分の過ちは素直に認めている。
A23: 21 | C23: メンバー育成 | D23: メンバーの育成課題を明確に、業務の割り当てや将来のキャリアを考えた育成計画を具体的に示している。 | E23: 3
A24: 22 | B24: 検証 | C24: 検証 | D24: 自部門の活動計画に対する実績を検証し、必要に応じて目標や活動計画の見直しを行っている。 | E24: 3
A25: 23 | D25: 成功例や失敗例の共有ができている。
A26: 24 | C26: リスク管理 | D26: 職場の安全（衛生）を優先した安全確保を意識し、交通ルールも遵守している。 | E26: 3
A27: 25 | D27: 自部門で予測される問題点を適宜把握しており、未然に防いでいる。
A28: 26 | C28: トラブル発生時の対応 | D28: 発生したトラブルを、重要度や優先順位の観点から必要な対応策を定め、実践している。 | E28: 3
A29: 27 | B29: 基本 | C29: ビジネス感覚 | D29: 一般教養、基本的なマネジメントや財務・会計等の知識やスキルを自ら取得し、現場で活用している。 | E29: 2
A30: 28 | D30: 自社や自部門の利益や費用（コスト）対効果を見極めて判断している。
A31: 29 | C31: 顧客志向 | D31: 顧客や取引先との交渉や折衝を円滑に行い、WIN・WINの関係になるようその関係を維持・構築している。 | E31: 2
A32: 30 | D32: ステークホルダーそれぞれのニーズを把握し、対応している。
A33: 31 | C33: 上級管理職志向 | D33: パワハラやセクハラ、また育児休業などの社内対応ルールを正しく理解し、必要がある際には対応できている。 | E33: 3
A34: 32 | D34: 自己と会社の狭間において、会社やメンバーのことを真剣に考えた言動をとっている。
B35: 評定… | C35: 以下の5段階とする | D35: 合計点 | E35: =SUM(E3:E34) -> 40
B36: 5点… | C36: 期待を大きく上回っている | D36: 100点換算（75点） | E36: =100/75*E35 -> 53.333333
B37: 4点… | C37: 期待を上回っている
B38: 3点… | C38: ほぼ期待通りである
B39: 2点… | C39: 期待にいま一歩である
B40: 1点… | C40: 期待を大きく下回っている

Sheet 管理職_KGL
B1: 管理職評価 | D1: スマイディアの管理職に必要な基礎能力と具体的実施行動
A2: 番号 | B2: 大項目 | C2: 中項目 | D2: 小項目（具体的行動内容） | E2: 上司評定
A3: 1 | B3: 課題認識 | C3: 情報収集 | D3: 新聞、業界紙、インターネットに加えて、社内外の人脈を通じて、会社及び自部門に関わる情報を入手している | E3: 3
A4: 2 | C4: 分析的・本質的課題認識 | D4: 取得した情報を正確・的確に分析したうえで、自部門の課題を明らかにしている。 | E4: 2
A5: 3 | B5: 企画・立案 | C5: あるべき姿・部門目標設定 | D5: 会社方針を踏まえて、自部門のあるべき姿・目標（ゴールイメージ）を明確にしている。 | E5: 3
A6: 4 | C6: 課題設定 | D6: 部門目標を踏まえ、顧客ニーズや部外環境の動向を想定し課題を設定している。 | E6: 1
A7: 5 | D7: 部門目標を達成するために重点課題を整理し、具体的な活動計画に落とし込むための方向性をメンバーの意見も傾聴し共有できている。
A8: 6 | C8: 体制立案 | D8: 重点課題解決に必要となる組織構成・人員・予算等の体制を立案し、会社に具申している。 | E8: 1
A9: 7 | C9: 実現性のある活動計画設定 | D9: 既成概念打破・創意工夫のある活動計画を設定している。 | E9: 4
A10: 8 | D10: 論理的に考えられた活動計画である。
A11: 9 | D11: 生産性の向上のための施策を織り込んでいる。
A12: 10 | D12: タイムスケジュールまで落とし込まれている。
A13: 11 | D13: 状況の変化に対応したり、業務拡大のための複数のシナリオが想定されている。
A14: 12 | D14: メンバー一人ひとりが主体的に取り組めるように具体的活動計画を理解させている。
A15: 13 | B15: 仕事の遂行 | C15: 実行 | D15: 困難な課題であっても合理的に考え、タイミングを逸することなく決断し、結果にコミットする努力を惜しまない。 | E15: 3
A16: 14 | D16: 「できない」ではなく、できる方法やどうすればできるかを考え実践している。
A17: 15 | D17: 率先垂範でメンバーから目標となる存在になっている。
A18: 16 | B18: 周囲への働きかけ | C18: 進捗管理と支援 | D18: 自部門だけでなく会社全体の業績向上という視点をもって、他部署に協力している。 | E18: 2
A19: 17 | D19: より大きな成果を出すためには、摩擦を恐れず既存の枠組みを変えていくように周囲に働きかけている。
A20: 18 | D20: 指示や支援、相談、叱咤激励などを通じて、目標達成へのメンバーへのこだわりを駆り立てている。
A21: 19 | D21: メンバーとは率先してコミュニケーションを行い、チームワークを高めている。
A22: 20 | D22: 自分の過ちは素直に認めている。
A23: 21 | C23: メンバー育成 | D23: メンバーの育成課題を明確に、業務の割り当てや将来のキャリアを考えた育成計画を具体的に示している。 | E23: 1
A24: 22 | B24: 検証 | C24: 検証 | D24: 自部門の活動計画に対する実績を検証し、必要に応じて目標や活動計画の見直しを行っている。 | E24: 3
A25: 23 | D25: 成功例や失敗例の共有ができている。
A26: 24 | C26: リスク管理 | D26: 職場の安全（衛生）を優先した安全確保を意識し、交通ルールも遵守している。 | E26: 3
A27: 25 | D27: 自部門で予測される問題点を適宜把握しており、未然に防いでいる。
A28: 26 | C28: トラブル発生時の対応 | D28: 発生したトラブルを、重要度や優先順位の観点から必要な対応策を定め、実践している。 | E28: 2
A29: 27 | B29: 基本 | C29: ビジネス感覚 | D29: 一般教養、基本的なマネジメントや財務・会計等の知識やスキルを自ら取得し、現場で活用している。 | E29: 2
A30: 28 | D30: 自社や自部門の利益や費用（コスト）対効果を見極めて判断している。
A31: 29 | C31: 顧客志向 | D31: 顧客や取引先との交渉や折衝を円滑に行い、WIN・WINの関係になるようその関係を維持・構築している。 | E31: 3
A32: 30 | D32: ステークホルダーそれぞれのニーズを把握し、対応している。
A33: 31 | C33: 上級管理職志向 | D33: パワハラやセクハラ、また育児休業などの社内対応ルールを正しく理解し、必要がある際には対応できている。 | E33: 3
A34: 32 | D34: 自己と会社の狭間において、会社やメンバーのことを真剣に考えた言動をとっている。
B35: 評定… | C35: 以下の5段階とする | D35: 合計点 | E35: =SUM(E3:E34) -> 36
B36: 5点… | C36: 期待を大きく上回っている | D36: 100点換算（75点） | E36: =100/75*E35 -> 48
B37: 4点… | C37: 期待を上回っている
B38: 3点… | C38: ほぼ期待通りである
B39: 2点… | C39: 期待にいま一歩である
B40: 1点… | C40: 期待を大きく下回っている
